VERILOG/tspc.v
`ifndef FLIPFLOP_V
`define FLIPFLOP_V
`timescale 1ns / 1ps

module flipflop_a(D_in, clk_signal, Q_out, Qbar_out);
  
  input D_in; 
  input clk_signal; 
  output Q_out;
  output Qbar_out;

  wire net_1;
  wire net_2;
  wire net_3;
  wire net_4;
  wire net_5;
  wire net_6;

  not not_gate1 (clk_not, clk_signal);

  not not_gate2 (D_not, D_in);
  nand nand_gate1 (net_1, D_in, clk_not);
  nand nand_gate2 (net_2, D_not, clk_not);
  nand nand_gate3 (net_3, net_1, net_4);
  nand nand_gate4 (net_4, net_2, net_3);
  
  nand nand_gate5 (net_5, net_3, clk_signal);
  nand nand_gate6 (net_6, net_4, clk_signal);
  nand nand_gate7 (Q_out, net_5, Qbar_out);
  nand nand_gate8 (Qbar_out, net_6, Q_out);

endmodule 

module flipflop_b(D_input, clk_in, Q_output, Qbar_output);
  
  input D_input; 
  input clk_in; 
  output Q_output;
  output Qbar_output;

  wire node_1;
  wire node_2;
  wire node_3;
  wire node_4;
  wire node_5;
  wire node_6;

  not not_gate_a (clk_inverted, clk_in);

  not not_gate_b (D_inverted, D_input);
  nand nand_gate_a (node_1, D_input, clk_in);
  nand nand_gate_b (node_2, D_inverted, clk_in);
  nand nand_gate_c (node_3, node_1, node_4);
  nand nand_gate_d (node_4, node_2, node_3);
  
  nand nand_gate_e (node_5, node_3, clk_inverted);
  nand nand_gate_f (node_6, node_4, clk_inverted);
  nand nand_gate_g (Q_output, node_5, Qbar_output);
  nand nand_gate_h (Qbar_output, node_6, Q_output);

endmodule 
`endif

VERILOG/tspc_tb.v
`timescale 1ns / 1ps

module flipflop_testbench;

  reg data_input;
  reg clock_signal;
	
  wire output_q1;
  wire output_qbar1;
  wire output_q2;
  wire output_qbar2;

  flipflop_b flipflop_inst1 (
    .D_input(data_input),
    .clk_in(clock_signal),
    .Q_output(output_q1),
    .Qbar_output(output_qbar1)
  );

  flipflop_a flipflop_inst2 (
    .D_in(data_input),
    .clk_signal(clock_signal),
    .Q_out(output_q2),
    .Qbar_out(output_qbar2)
  );
  
  initial begin 
    $dumpfile("flipflop_wave.vcd");
    $dumpvars(0, flipflop_testbench);
    clock_signal = 0;
    data_input = 0;

    #10 clock_signal = ~clock_signal;
        data_input = 1;
    #10 clock_signal = ~clock_signal;
    #10 clock_signal = ~clock_signal;
        data_input = 0;
    #10 clock_signal = ~clock_signal;
    #10 clock_signal = ~clock_signal;
        data_input = 1;
    #10 clock_signal = ~clock_signal;
    #10 clock_signal = ~clock_signal;
        data_input = 1;
    #10 clock_signal = ~clock_signal;
        data_input = 0;
    #10 clock_signal = ~clock_signal;
        data_input = 1;
    #10 clock_signal = ~clock_signal;
    #10 clock_signal = ~clock_signal;
    #10 clock_signal = ~clock_signal;
    #10 clock_signal = ~clock_signal;
  end 
  
  initial 
    $monitor("D=%d clk=%d Q1=%d Qbar1=%d Q2=%d Qbar2=%d", data_input, clock_signal, output_q1, output_qbar1, output_q2, output_qbar2);
endmodule

VERILOG/flipflop_wave.vcd
$date
	Mon Nov 18 22:05:28 2024
$end
$version
	Icarus Verilog
$end
$timescale
	1ps
$end
$scope module flipflop_testbench $end
$var wire 1 ! output_qbar2 $end
$var wire 1 " output_qbar1 $end
$var wire 1 # output_q2 $end
$var wire 1 $ output_q1 $end
$var reg 1 % clock_signal $end
$var reg 1 & data_input $end
$scope module flipflop_inst1 $end
$var wire 1 & D_input $end
$var wire 1 ' D_inverted $end
$var wire 1 $ Q_output $end
$var wire 1 " Qbar_output $end
$var wire 1 % clk_in $end
$var wire 1 ( clk_inverted $end
$var wire 1 ) node_1 $end
$var wire 1 * node_2 $end
$var wire 1 + node_3 $end
$var wire 1 , node_4 $end
$var wire 1 - node_5 $end
$var wire 1 . node_6 $end
$upscope $end
$scope module flipflop_inst2 $end
$var wire 1 & D_in $end
$var wire 1 / D_not $end
$var wire 1 # Q_out $end
$var wire 1 ! Qbar_out $end
$var wire 1 0 clk_not $end
$var wire 1 % clk_signal $end
$var wire 1 1 net_1 $end
$var wire 1 2 net_2 $end
$var wire 1 3 net_3 $end
$var wire 1 4 net_4 $end
$var wire 1 5 net_5 $end
$var wire 1 6 net_6 $end
$upscope $end
$upscope $end
$enddefinitions $end
#0
$dumpvars
16
15
14
03
02
11
10
1/
x.
x-
x,
x+
1*
1)
1(
1'
0&
0%
x$
x#
x"
x!
$end
#10000
0#
1-
1.
1+
0,
12
1!
0'
0/
0(
0)
1*
00
06
1&
1%
#20000
0"
04
1$
13
0-
01
1(
1)
10
16
0%
#30000
0+
1,
0!
0*
1-
1#
1'
1/
11
0(
00
05
0&
1%
#40000
0$
03
1"
14
0.
02
1(
1*
10
15
0%
#50000
0,
0#
1.
1+
12
1!
0'
0/
0(
0)
1*
00
06
1&
1%
#60000
0"
04
1$
13
0-
01
1(
1)
10
16
0%
#70000
0!
1-
11
1#
0(
0)
00
05
1%
#80000
03
14
0-
02
1'
1/
1(
1)
10
15
0&
0%
#90000
0#
1-
0,
12
1!
0'
0/
0(
0)
1*
00
06
1&
1%
#100000
04
13
0-
01
1(
1)
10
16
0%
#110000
0!
1-
11
1#
0(
0)
00
05
1%
#120000
0-
01
1(
1)
10
15
0%
#130000
1-
11
0(
0)
00
05
1%
