VERILOG/tspc.v
`ifndef FLIPFLOP_V
`define FLIPFLOP_V
`timescale 1ns / 1ps

module flipflop_a(D_in, clk_signal, Q_out, Qbar_out);
  
  input D_in; 
  input clk_signal; 
  output Q_out;
  output Qbar_out;

  wire net_1;
  wire net_2;
  wire net_3;
  wire net_4;
  wire net_5;
  wire net_6;

  not not_gate1 (clk_not, clk_signal);

  not not_gate2 (D_not, D_in);
  nand nand_gate1 (net_1, D_in, clk_not);
  nand nand_gate2 (net_2, D_not, clk_not);
  nand nand_gate3 (net_3, net_1, net_4);
  nand nand_gate4 (net_4, net_2, net_3);
  
  nand nand_gate5 (net_5, net_3, clk_signal);
  nand nand_gate6 (net_6, net_4, clk_signal);
  nand nand_gate7 (Q_out, net_5, Qbar_out);
  nand nand_gate8 (Qbar_out, net_6, Q_out);

endmodule 

module flipflop_b(D_input, clk_in, Q_output, Qbar_output);
  
  input D_input; 
  input clk_in; 
  output Q_output;
  output Qbar_output;

  wire node_1;
  wire node_2;
  wire node_3;
  wire node_4;
  wire node_5;
  wire node_6;

  not not_gate_a (clk_inverted, clk_in);

  not not_gate_b (D_inverted, D_input);
  nand nand_gate_a (node_1, D_input, clk_in);
  nand nand_gate_b (node_2, D_inverted, clk_in);
  nand nand_gate_c (node_3, node_1, node_4);
  nand nand_gate_d (node_4, node_2, node_3);
  
  nand nand_gate_e (node_5, node_3, clk_inverted);
  nand nand_gate_f (node_6, node_4, clk_inverted);
  nand nand_gate_g (Q_output, node_5, Qbar_output);
  nand nand_gate_h (Qbar_output, node_6, Q_output);

endmodule 
`endif

VERILOG/carry_look_ahead_gen.v
`ifndef CARRY_LOOK_AHEAD_GEN_V
`define CARRY_LOOK_AHEAD_GEN_V

`timescale 1ns / 1ps

module carry_look_ahead_gen(p1, g1, p0, g0, l, n);

  input p1, g1, p0, g0;
  output l, n;

  nor nor_inst1(l, p1, p0);
  or or_inst1(o_temp, p1, g0);
  nand nand_inst1(n, o_temp, g1);

endmodule
`endif

VERILOG/prop_gen.v
`ifndef PROP_GEN_V
`define PROP_GEN_V

`timescale 1ns / 1ps

module prop_gen(x, y, p, g, k);

  input x, y;
  output p, g, k;

  nor nor_inst1(p, x, y);
  nand nand_inst1(g, x, y);
  xor xor_inst1(k, x, y);

endmodule
`endif

VERILOG/carry_look_ahead.v
`ifndef CARRY_LOOK_AHEAD_V
`define CARRY_LOOK_AHEAD_V
`timescale 1ns / 1ps

`include "prop_gen.v"
`include "carry_look_ahead_gen.v"

module carry_look_ahead(a1, a2, a3, a4, b1, b2, b3, b4, cin, o1, o2, o3, o4, cout);

  input a1, a2, a3, a4;
  input b1, b2, b3, b4;
  input cin;

  output o1, o2, o3, o4, cout;

  wire p1, p2, p3, p4;
  wire g1, g2, g3, g4;
  wire k1, k2, k3, k4;

  prop_gen pg_inst1 (.x(a1), .y(b1), .p(p1), .g(g1), .k(k1));
  prop_gen pg_inst2 (.x(a2), .y(b2), .p(p2), .g(g2), .k(k2));
  prop_gen pg_inst3 (.x(a3), .y(b3), .p(p3), .g(g3), .k(k3));
  prop_gen pg_inst4 (.x(a4), .y(b4), .p(p4), .g(g4), .k(k4));

  not not_inst1(cinnot, cin);
  or or_inst1(o1_temp, cinnot, p1);
  nand nand_inst1(n1_temp, o1_temp, g1);

  carry_look_ahead_gen clg_inst2 (.p1(p2), .g1(g2), .p0(p1), .g0(g1), .l(l2), .n(n2));
  carry_look_ahead_gen clg_inst3 (.p1(p3), .g1(g3), .p0(p2), .g0(g2), .l(l3), .n(n3));
  carry_look_ahead_gen clg_inst4 (.p1(p4), .g1(g4), .p0(p3), .g0(g3), .l(l4), .n(n4));

  xor xor_inst1(o1, cin, k1);
  xor xor_inst2(o2, n1_temp, k2);

  and and_inst1(o2_temp, cin, l2);
  or or_inst2(c3_temp, o2_temp, n2);
  xor xor_inst3(o3, c3_temp, k3);

  and and_inst2(o3_temp, n1_temp, l3);
  or or_inst3(c4_temp, o3_temp, n3);
  xor xor_inst4(o4, c4_temp, k4);

  nand nand_inst2(po_not, l2, l4);
  and and_inst3(o4_temp, l4, n2);
  nor nor_inst2(go_not, o4_temp, n4);

  not not_inst2(go, go_not);
  not not_inst3(po, po_not);

  and and_inst4(o5_temp, cin, po);
  or or_inst4(cout, go, o5_temp);

endmodule
`endif

VERILOG/final.v
`ifndef FINAL_V
`define FINAL_V

`timescale 1ns / 1ps

`include "carry_look_ahead.v"
`include "tspc.v"

module toplevel(clk, a, b, ci, co, s);
  
  input clk;
  input [4:1] a;  
  input [4:1] b;  
  input ci;   
  
  output co;      
  output [4:1] s; 

  wire a1_ff, a2_ff, a3_ff, a4_ff;
  wire b1_ff, b2_ff, b3_ff, b4_ff;

  wire ci_ff;
  wire co_temp;

  wire s1_temp, s2_temp, s3_temp, s4_temp;

  flipflop_a ff_ci(.D_in(ci), .clk_signal(clk), .Q_out(ci_ff));
  flipflop_a ff_a1(.D_in(a[1]), .clk_signal(clk), .Q_out(a1_ff));
  flipflop_a ff_a2(.D_in(a[2]), .clk_signal(clk), .Q_out(a2_ff));
  flipflop_a ff_a3(.D_in(a[3]), .clk_signal(clk), .Q_out(a3_ff));
  flipflop_a ff_a4(.D_in(a[4]), .clk_signal(clk), .Q_out(a4_ff));
  flipflop_a ff_b1(.D_in(b[1]), .clk_signal(clk), .Q_out(b1_ff));
  flipflop_a ff_b2(.D_in(b[2]), .clk_signal(clk), .Q_out(b2_ff));
  flipflop_a ff_b3(.D_in(b[3]), .clk_signal(clk), .Q_out(b3_ff));
  flipflop_a ff_b4(.D_in(b[4]), .clk_signal(clk), .Q_out(b4_ff));


  carry_look_ahead cla_inst(
    .a1(a1_ff), .a2(a2_ff), .a3(a3_ff), .a4(a4_ff),
    .b1(b1_ff), .b2(b2_ff), .b3(b3_ff), .b4(b4_ff),
    .cin(ci_ff),
    .o1(s1_temp), .o2(s2_temp), .o3(s3_temp), .o4(s4_temp),
    .cout(co_temp)
  );

  flipflop_b ff_s1(.D_input(s1_temp), .clk_in(clk), .Q_output(s[1]));
  flipflop_b ff_s2(.D_input(s2_temp), .clk_in(clk), .Q_output(s[2]));
  flipflop_b ff_s3(.D_input(s3_temp), .clk_in(clk), .Q_output(s[3]));
  flipflop_b ff_s4(.D_input(s4_temp), .clk_in(clk), .Q_output(s[4]));
  flipflop_b ff_co(.D_input(co_temp), .clk_in(clk), .Q_output(co));

endmodule
`endif

VERILOG/final_tb.v
`timescale 1ns / 1ps

`include "final.v"

module tb;

  reg clk;
  reg ci;                 // Carry-in (renamed from cin)
  reg [4:1] a, b;         // Inputs (renamed from x, y)

  wire co;                // Carry-out (renamed from cout)
  wire [4:1] s;           // Sum outputs (renamed from z)

  // Instantiate the top-level module
  toplevel dut(
    .clk  (clk ),
    .a    (a   ),         // Aligned to input `a` in final.v
    .b    (b   ),         // Aligned to input `b` in final.v
    .ci   (ci  ),         // Aligned to input `ci` in final.v
    .co   (co  ),         // Aligned to output `co` in final.v
    .s    (s   )          // Aligned to output `s` in final.v
  );

  // Clock generation
  always #5 clk = ~clk;

  // Initialize signals and apply test cases
  initial begin 
    // Initialize waveform dump for VCD file
    $dumpfile("test.vcd");
    $dumpvars(0, tb);

    // Initialize input signals
    clk = 0;

    // Apply 15 carefully chosen test cases
    #10 a = 4'b0000; b = 4'b0000; ci = 0;  // Case 1: All zeros
    #10 a = 4'b0001; b = 4'b0001; ci = 0;  // Case 2: Simple addition
    #10 a = 4'b0010; b = 4'b0011; ci = 1;  // Case 3: Addition with carry-in
    #10 a = 4'b1111; b = 4'b0000; ci = 0;  // Case 4: Max a, zero b
    #10 a = 4'b0000; b = 4'b1111; ci = 0;  // Case 5: Zero a, max b
    #10 a = 4'b1111; b = 4'b1111; ci = 0;  // Case 6: Max a and b, no carry-in
    #10 a = 4'b1111; b = 4'b1111; ci = 1;  // Case 7: Max a and b, with carry-in
    #10 a = 4'b1000; b = 4'b1000; ci = 0;  // Case 8: Test overflow
    #10 a = 4'b1000; b = 4'b1000; ci = 1;  // Case 9: Overflow with carry-in
    #10 a = 4'b0101; b = 4'b0011; ci = 0;  // Case 10: Intermediate values
    #10 a = 4'b0101; b = 4'b0011; ci = 1;  // Case 11: Intermediate with carry-in
    #10 a = 4'b0110; b = 4'b1001; ci = 0;  // Case 12: Random combination
    #10 a = 4'b0110; b = 4'b1001; ci = 1;  // Case 13: Random with carry-in
    #10 a = 4'b0111; b = 4'b0111; ci = 0;  // Case 14: Symmetrical
    #10 a = 4'b0111; b = 4'b0111; ci = 1;  // Case 15: Symmetrical with carry-in

    // End simulation after 15 cases
    #50 $finish;
  end

  // Monitor the signals during simulation
  initial begin
    $monitor("clk=%b a=%b b=%b ci=%b co=%b s=%b", clk, a, b, ci, co, s);
  end

endmodule

VERILOG/test.vcd
$date
	Mon Nov 18 22:17:49 2024
$end
$version
	Icarus Verilog
$end
$timescale
	1ps
$end
$scope module tb $end
$var wire 4 ! s [4:1] $end
$var wire 1 " co $end
$var reg 4 # a [4:1] $end
$var reg 4 $ b [4:1] $end
$var reg 1 % ci $end
$var reg 1 & clk $end
$scope module dut $end
$var wire 4 ' a [4:1] $end
$var wire 4 ( b [4:1] $end
$var wire 1 % ci $end
$var wire 1 & clk $end
$var wire 1 ) s4_temp $end
$var wire 1 * s3_temp $end
$var wire 1 + s2_temp $end
$var wire 1 , s1_temp $end
$var wire 4 - s [4:1] $end
$var wire 1 . co_temp $end
$var wire 1 " co $end
$var wire 1 / ci_ff $end
$var wire 1 0 b4_ff $end
$var wire 1 1 b3_ff $end
$var wire 1 2 b2_ff $end
$var wire 1 3 b1_ff $end
$var wire 1 4 a4_ff $end
$var wire 1 5 a3_ff $end
$var wire 1 6 a2_ff $end
$var wire 1 7 a1_ff $end
$scope module cla_inst $end
$var wire 1 8 c3_temp $end
$var wire 1 9 c4_temp $end
$var wire 1 : cinnot $end
$var wire 1 . cout $end
$var wire 1 ; go $end
$var wire 1 < go_not $end
$var wire 1 = n1_temp $end
$var wire 1 , o1 $end
$var wire 1 > o1_temp $end
$var wire 1 + o2 $end
$var wire 1 ? o2_temp $end
$var wire 1 * o3 $end
$var wire 1 @ o3_temp $end
$var wire 1 ) o4 $end
$var wire 1 A o4_temp $end
$var wire 1 B o5_temp $end
$var wire 1 C po $end
$var wire 1 D po_not $end
$var wire 1 E p4 $end
$var wire 1 F p3 $end
$var wire 1 G p2 $end
$var wire 1 H p1 $end
$var wire 1 I n4 $end
$var wire 1 J n3 $end
$var wire 1 K n2 $end
$var wire 1 L l4 $end
$var wire 1 M l3 $end
$var wire 1 N l2 $end
$var wire 1 O k4 $end
$var wire 1 P k3 $end
$var wire 1 Q k2 $end
$var wire 1 R k1 $end
$var wire 1 S g4 $end
$var wire 1 T g3 $end
$var wire 1 U g2 $end
$var wire 1 V g1 $end
$var wire 1 / cin $end
$var wire 1 0 b4 $end
$var wire 1 1 b3 $end
$var wire 1 2 b2 $end
$var wire 1 3 b1 $end
$var wire 1 4 a4 $end
$var wire 1 5 a3 $end
$var wire 1 6 a2 $end
$var wire 1 7 a1 $end
$scope module clg_inst2 $end
$var wire 1 N l $end
$var wire 1 K n $end
$var wire 1 W o_temp $end
$var wire 1 G p1 $end
$var wire 1 H p0 $end
$var wire 1 U g1 $end
$var wire 1 V g0 $end
$upscope $end
$scope module clg_inst3 $end
$var wire 1 M l $end
$var wire 1 J n $end
$var wire 1 X o_temp $end
$var wire 1 F p1 $end
$var wire 1 G p0 $end
$var wire 1 T g1 $end
$var wire 1 U g0 $end
$upscope $end
$scope module clg_inst4 $end
$var wire 1 L l $end
$var wire 1 I n $end
$var wire 1 Y o_temp $end
$var wire 1 E p1 $end
$var wire 1 F p0 $end
$var wire 1 S g1 $end
$var wire 1 T g0 $end
$upscope $end
$scope module pg_inst1 $end
$var wire 1 V g $end
$var wire 1 R k $end
$var wire 1 H p $end
$var wire 1 3 y $end
$var wire 1 7 x $end
$upscope $end
$scope module pg_inst2 $end
$var wire 1 U g $end
$var wire 1 Q k $end
$var wire 1 G p $end
$var wire 1 2 y $end
$var wire 1 6 x $end
$upscope $end
$scope module pg_inst3 $end
$var wire 1 T g $end
$var wire 1 P k $end
$var wire 1 F p $end
$var wire 1 1 y $end
$var wire 1 5 x $end
$upscope $end
$scope module pg_inst4 $end
$var wire 1 S g $end
$var wire 1 O k $end
$var wire 1 E p $end
$var wire 1 0 y $end
$var wire 1 4 x $end
$upscope $end
$upscope $end
$scope module ff_a1 $end
$var wire 1 Z D_in $end
$var wire 1 [ D_not $end
$var wire 1 7 Q_out $end
$var wire 1 \ Qbar_out $end
$var wire 1 ] clk_not $end
$var wire 1 & clk_signal $end
$var wire 1 ^ net_1 $end
$var wire 1 _ net_2 $end
$var wire 1 ` net_3 $end
$var wire 1 a net_4 $end
$var wire 1 b net_5 $end
$var wire 1 c net_6 $end
$upscope $end
$scope module ff_a2 $end
$var wire 1 d D_in $end
$var wire 1 e D_not $end
$var wire 1 6 Q_out $end
$var wire 1 f Qbar_out $end
$var wire 1 g clk_not $end
$var wire 1 & clk_signal $end
$var wire 1 h net_1 $end
$var wire 1 i net_2 $end
$var wire 1 j net_3 $end
$var wire 1 k net_4 $end
$var wire 1 l net_5 $end
$var wire 1 m net_6 $end
$upscope $end
$scope module ff_a3 $end
$var wire 1 n D_in $end
$var wire 1 o D_not $end
$var wire 1 5 Q_out $end
$var wire 1 p Qbar_out $end
$var wire 1 q clk_not $end
$var wire 1 & clk_signal $end
$var wire 1 r net_1 $end
$var wire 1 s net_2 $end
$var wire 1 t net_3 $end
$var wire 1 u net_4 $end
$var wire 1 v net_5 $end
$var wire 1 w net_6 $end
$upscope $end
$scope module ff_a4 $end
$var wire 1 x D_in $end
$var wire 1 y D_not $end
$var wire 1 4 Q_out $end
$var wire 1 z Qbar_out $end
$var wire 1 { clk_not $end
$var wire 1 & clk_signal $end
$var wire 1 | net_1 $end
$var wire 1 } net_2 $end
$var wire 1 ~ net_3 $end
$var wire 1 !" net_4 $end
$var wire 1 "" net_5 $end
$var wire 1 #" net_6 $end
$upscope $end
$scope module ff_b1 $end
$var wire 1 $" D_in $end
$var wire 1 %" D_not $end
$var wire 1 3 Q_out $end
$var wire 1 &" Qbar_out $end
$var wire 1 '" clk_not $end
$var wire 1 & clk_signal $end
$var wire 1 (" net_1 $end
$var wire 1 )" net_2 $end
$var wire 1 *" net_3 $end
$var wire 1 +" net_4 $end
$var wire 1 ," net_5 $end
$var wire 1 -" net_6 $end
$upscope $end
$scope module ff_b2 $end
$var wire 1 ." D_in $end
$var wire 1 /" D_not $end
$var wire 1 2 Q_out $end
$var wire 1 0" Qbar_out $end
$var wire 1 1" clk_not $end
$var wire 1 & clk_signal $end
$var wire 1 2" net_1 $end
$var wire 1 3" net_2 $end
$var wire 1 4" net_3 $end
$var wire 1 5" net_4 $end
$var wire 1 6" net_5 $end
$var wire 1 7" net_6 $end
$upscope $end
$scope module ff_b3 $end
$var wire 1 8" D_in $end
$var wire 1 9" D_not $end
$var wire 1 1 Q_out $end
$var wire 1 :" Qbar_out $end
$var wire 1 ;" clk_not $end
$var wire 1 & clk_signal $end
$var wire 1 <" net_1 $end
$var wire 1 =" net_2 $end
$var wire 1 >" net_3 $end
$var wire 1 ?" net_4 $end
$var wire 1 @" net_5 $end
$var wire 1 A" net_6 $end
$upscope $end
$scope module ff_b4 $end
$var wire 1 B" D_in $end
$var wire 1 C" D_not $end
$var wire 1 0 Q_out $end
$var wire 1 D" Qbar_out $end
$var wire 1 E" clk_not $end
$var wire 1 & clk_signal $end
$var wire 1 F" net_1 $end
$var wire 1 G" net_2 $end
$var wire 1 H" net_3 $end
$var wire 1 I" net_4 $end
$var wire 1 J" net_5 $end
$var wire 1 K" net_6 $end
$upscope $end
$scope module ff_ci $end
$var wire 1 % D_in $end
$var wire 1 L" D_not $end
$var wire 1 / Q_out $end
$var wire 1 M" Qbar_out $end
$var wire 1 N" clk_not $end
$var wire 1 & clk_signal $end
$var wire 1 O" net_1 $end
$var wire 1 P" net_2 $end
$var wire 1 Q" net_3 $end
$var wire 1 R" net_4 $end
$var wire 1 S" net_5 $end
$var wire 1 T" net_6 $end
$upscope $end
$scope module ff_co $end
$var wire 1 . D_input $end
$var wire 1 U" D_inverted $end
$var wire 1 " Q_output $end
$var wire 1 V" Qbar_output $end
$var wire 1 & clk_in $end
$var wire 1 W" clk_inverted $end
$var wire 1 X" node_1 $end
$var wire 1 Y" node_2 $end
$var wire 1 Z" node_3 $end
$var wire 1 [" node_4 $end
$var wire 1 \" node_5 $end
$var wire 1 ]" node_6 $end
$upscope $end
$scope module ff_s1 $end
$var wire 1 , D_input $end
$var wire 1 ^" D_inverted $end
$var wire 1 _" Q_output $end
$var wire 1 `" Qbar_output $end
$var wire 1 & clk_in $end
$var wire 1 a" clk_inverted $end
$var wire 1 b" node_1 $end
$var wire 1 c" node_2 $end
$var wire 1 d" node_3 $end
$var wire 1 e" node_4 $end
$var wire 1 f" node_5 $end
$var wire 1 g" node_6 $end
$upscope $end
$scope module ff_s2 $end
$var wire 1 + D_input $end
$var wire 1 h" D_inverted $end
$var wire 1 i" Q_output $end
$var wire 1 j" Qbar_output $end
$var wire 1 & clk_in $end
$var wire 1 k" clk_inverted $end
$var wire 1 l" node_1 $end
$var wire 1 m" node_2 $end
$var wire 1 n" node_3 $end
$var wire 1 o" node_4 $end
$var wire 1 p" node_5 $end
$var wire 1 q" node_6 $end
$upscope $end
$scope module ff_s3 $end
$var wire 1 * D_input $end
$var wire 1 r" D_inverted $end
$var wire 1 s" Q_output $end
$var wire 1 t" Qbar_output $end
$var wire 1 & clk_in $end
$var wire 1 u" clk_inverted $end
$var wire 1 v" node_1 $end
$var wire 1 w" node_2 $end
$var wire 1 x" node_3 $end
$var wire 1 y" node_4 $end
$var wire 1 z" node_5 $end
$var wire 1 {" node_6 $end
$upscope $end
$scope module ff_s4 $end
$var wire 1 ) D_input $end
$var wire 1 |" D_inverted $end
$var wire 1 }" Q_output $end
$var wire 1 ~" Qbar_output $end
$var wire 1 & clk_in $end
$var wire 1 !# clk_inverted $end
$var wire 1 "# node_1 $end
$var wire 1 ## node_2 $end
$var wire 1 $# node_3 $end
$var wire 1 %# node_4 $end
$var wire 1 &# node_5 $end
$var wire 1 '# node_6 $end
$upscope $end
$upscope $end
$upscope $end
$enddefinitions $end
#0
$dumpvars
x'#
x&#
x%#
x$#
1##
1"#
1!#
x~"
x}"
x|"
x{"
xz"
xy"
xx"
1w"
1v"
1u"
xt"
xs"
xr"
xq"
xp"
xo"
xn"
1m"
1l"
1k"
xj"
xi"
xh"
xg"
xf"
xe"
xd"
1c"
1b"
1a"
x`"
x_"
x^"
x]"
x\"
x["
xZ"
1Y"
1X"
1W"
xV"
xU"
1T"
1S"
xR"
xQ"
xP"
xO"
1N"
xM"
xL"
1K"
1J"
xI"
xH"
xG"
xF"
1E"
xD"
xC"
xB"
1A"
1@"
x?"
x>"
x="
x<"
1;"
x:"
x9"
x8"
17"
16"
x5"
x4"
x3"
x2"
11"
x0"
x/"
x."
1-"
1,"
x+"
x*"
x)"
x("
1'"
x&"
x%"
x$"
1#"
1""
x!"
x~
x}
x|
1{
xz
xy
xx
1w
1v
xu
xt
xs
xr
1q
xp
xo
xn
1m
1l
xk
xj
xi
xh
1g
xf
xe
xd
1c
1b
xa
x`
x_
x^
1]
x\
x[
xZ
xY
xX
xW
xV
xU
xT
xS
xR
xQ
xP
xO
xN
xM
xL
xK
xJ
xI
xH
xG
xF
xE
xD
xC
xB
xA
x@
x?
x>
x=
x<
x;
x:
x9
x8
x7
x6
x5
x4
x3
x2
x1
x0
x/
x.
bx -
x,
x+
x*
x)
bx (
bx '
0&
x%
bx $
bx #
x"
bx !
$end
#5000
1^
1_
1h
1i
1r
1s
1|
1}
1("
1)"
12"
13"
1<"
1="
1F"
1G"
1O"
1P"
1\"
1]"
1f"
1g"
1p"
1q"
1z"
1{"
1&#
1'#
0]
xb
xc
0g
xl
xm
0q
xv
xw
0{
x""
x#"
0'"
x,"
x-"
01"
x6"
x7"
0;"
x@"
xA"
0E"
xJ"
xK"
0N"
xS"
xT"
0W"
xX"
xY"
0a"
xb"
xc"
0k"
xl"
xm"
0u"
xv"
xw"
0!#
x"#
x##
1&
#10000
0`
0j
0t
0~
0*"
04"
0>"
0H"
0Q"
1a
1k
1u
1!"
1+"
15"
1?"
1I"
1R"
0_
0i
0s
0}
0)"
03"
0="
0G"
x\"
x]"
xf"
xg"
xp"
xq"
xz"
x{"
x&#
x'#
0P"
1%"
1/"
19"
1C"
1[
1e
1o
1y
1]
1b
1c
1g
1l
1m
1q
1v
1w
1{
1""
1#"
1'"
1,"
1-"
11"
16"
17"
1;"
1@"
1A"
1E"
1J"
1K"
1N"
1S"
1T"
1W"
1X"
1Y"
1a"
1b"
1c"
1k"
1l"
1m"
1u"
1v"
1w"
1!#
1"#
1##
1L"
0$"
0."
08"
0B"
0Z
0d
0n
0x
0&
0%
b0 $
b0 (
b0 #
b0 '
#15000
0Z"
0x"
0$#
1["
0n"
1y"
1%#
0d"
1o"
1U"
1e"
1r"
1|"
0.
1h"
0*
0)
0;
0C
1^"
0+
08
09
0@
1<
0A
1D
0,
0=
0K
1W
0N
0J
1X
0M
0I
1Y
0L
1>
0R
1V
1H
0Q
1U
1G
0P
1T
1F
0O
1S
1E
0B
0?
1:
07
06
05
04
03
02
01
00
0/
1_
1\
1i
1f
1s
1p
1}
1z
1)"
1&"
13"
10"
1="
1:"
1G"
1D"
1P"
1M"
1\"
1]"
1f"
1g"
1p"
1q"
1z"
1{"
1&#
1'#
0]
0c
0g
0m
0q
0w
0{
0#"
0'"
0-"
01"
07"
0;"
0A"
0E"
0K"
0N"
0T"
0W"
1X"
0Y"
0a"
1b"
0c"
0k"
1l"
0m"
0u"
1v"
0w"
0!#
1"#
0##
1&
#20000
0"
0_"
0i"
0s"
b0 !
b0 -
0}"
0+"
0a
1V"
1`"
1j"
1t"
1~"
1*"
1`
0i
0s
0}
03"
0="
0G"
0P"
0]"
0g"
0q"
0{"
0'#
0%"
0("
0[
0^
1]
1c
1g
1m
1q
1w
1{
1#"
1'"
1-"
11"
17"
1;"
1A"
1E"
1K"
1N"
1T"
1W"
1Y"
1a"
1c"
1k"
1m"
1u"
1w"
1!#
1##
1$"
1Z
0&
b1 $
b1 (
b1 #
b1 '
#25000
0o"
1n"
0h"
0l"
1+
1=
0\
0&"
0V
0H
1^
17
1i
1s
1}
1("
13
13"
1="
1G"
1P"
1]"
1g"
1q"
1{"
1'#
0]
0b
0g
0m
0q
0w
0{
0#"
0'"
0,"
01"
07"
0;"
0A"
0E"
0K"
0N"
0T"
0W"
0Y"
0a"
0c"
0k"
1m"
0u"
0w"
0!#
0##
1&
#30000
0`
0R"
0j"
05"
0k
1a
1Q"
b10 !
b10 -
1i"
14"
1j
0_
0s
0}
0("
0="
0G"
0O"
0]"
0g"
0p"
0{"
0'#
0/"
02"
1[
0e
0h
1]
1b
1g
1m
1q
1w
1{
1#"
1'"
1,"
11"
17"
1;"
1A"
1E"
1K"
1N"
1T"
1W"
1Y"
1a"
1c"
1k"
1l"
1u"
1w"
1!#
1##
0L"
1."
0Z
1d
0&
1%
b11 $
b11 (
b10 #
b10 '
#35000
0y"
1x"
0r"
0v"
1*
1e"
18
1?
0d"
1R
1V
1K
1W
1N
1^"
1b"
0>
07
0f
00"
0U
0G
0M"
0,
0:
1_
1\
1h
16
1s
1}
1("
12"
12
1="
1G"
1O"
1/
1]"
1g"
1p"
1{"
1'#
0]
0c
0g
0l
0q
0w
0{
0#"
0'"
0,"
01"
06"
0;"
0A"
0E"
0K"
0N"
0S"
0W"
0Y"
0a"
0c"
0k"
0l"
0u"
1w"
0!#
0##
1&
#40000
0*"
04"
0t"
0Q"
0a
0u
0!"
1+"
15"
b110 !
b110 -
1s"
1R"
1`
1t
1~
0h
0)"
03"
0="
0G"
0]"
0g"
0p"
0z"
0'#
0P"
1%"
1/"
0[
0^
0o
0r
0y
0|
1]
1c
1g
1l
1q
1w
1{
1#"
1'"
1,"
11"
16"
1;"
1A"
1E"
1K"
1N"
1S"
1W"
1Y"
1a"
1c"
1k"
1l"
1u"
1v"
1!#
1##
1L"
0$"
0."
1Z
1n
1x
0&
0%
b0 $
b0 (
b1111 #
b1111 '
#45000
0o"
0y"
0%#
1m"
0e"
1w"
09
1$#
1C
0h"
08
1d"
0=
0r"
0@
0|"
0"#
0D
1+
0K
0^"
0b"
1>
1*
1M
1)
1L
1Q
1U
0?
1,
1:
0\
0p
1P
0F
0z
1O
0E
03
02
0/
1^
17
1h
1r
15
1|
14
1)"
1&"
13"
10"
1="
1G"
1P"
1M"
1]"
1g"
1p"
1z"
1'#
0]
0b
0g
0l
0q
0v
0{
0""
0'"
0-"
01"
07"
0;"
0A"
0E"
0K"
0N"
0T"
0W"
0Y"
0a"
1c"
0k"
0l"
0u"
0v"
0!#
1##
1&
#50000
0`
0j
0t
0~
0`"
0~"
0+"
05"
0?"
0I"
1a
1k
1u
1!"
1_"
b1111 !
b1111 -
1}"
1*"
14"
1>"
1H"
0_
0i
0s
0}
0P"
0]"
0f"
0p"
0z"
0&#
0%"
0("
0/"
02"
09"
0<"
0C"
0F"
1[
1e
1o
1y
1]
1b
1g
1l
1q
1v
1{
1""
1'"
1-"
11"
17"
1;"
1A"
1E"
1K"
1N"
1T"
1W"
1Y"
1a"
1b"
1k"
1l"
1u"
1v"
1!#
1"#
1$"
1."
18"
1B"
0Z
0d
0n
0x
0&
b1111 $
b1111 (
b0 #
b0 '
#55000
1["
0Z"
1x"
1$#
1U"
1X"
0e"
0o"
0y"
0%#
0.
1c"
1m"
1w"
1##
0;
0^"
0@
0h"
0A
08
0r"
09
0|"
1<
1,
1W
0=
1+
1X
0K
1*
1Y
0J
1)
0I
07
06
05
04
0&"
1R
1V
00"
1Q
1U
0:"
1P
1T
0D"
1O
1S
1_
1\
1i
1f
1s
1p
1}
1z
1("
13
12"
12
1<"
11
1F"
10
1P"
1]"
1f"
1p"
1z"
1&#
0]
0c
0g
0m
0q
0w
0{
0#"
0'"
0,"
01"
06"
0;"
0@"
0E"
0J"
0N"
0T"
0W"
0Y"
0a"
0b"
0k"
0l"
0u"
0v"
0!#
0"#
1&
#60000
0a
0k
0u
0!"
1`
1j
1t
1~
0("
02"
0<"
0F"
0P"
0]"
0f"
0p"
0z"
0&#
0[
0^
0e
0h
0o
0r
0y
0|
1]
1c
1g
1m
1q
1w
1{
1#"
1'"
1,"
11"
16"
1;"
1@"
1E"
1J"
1N"
1T"
1W"
1Y"
1a"
1b"
1k"
1l"
1u"
1v"
1!#
1"#
1Z
1d
1n
1x
0&
b1111 #
b1111 '
#65000
0["
1Z"
0d"
0U"
0X"
1e"
0o"
0y"
0%#
1.
0c"
1m"
1w"
1##
1;
1^"
1@
0h"
1A
18
0r"
19
0|"
0<
0,
0W
1=
1+
0X
1K
1*
0Y
1J
1)
1I
0\
0R
0V
0f
0Q
0U
0p
0P
0T
0z
0O
0S
1^
17
1h
16
1r
15
1|
14
1("
12"
1<"
1F"
1P"
1]"
1f"
1p"
1z"
1&#
0]
0b
0g
0l
0q
0v
0{
0""
0'"
0,"
01"
06"
0;"
0@"
0E"
0J"
0N"
0T"
0W"
1Y"
0a"
1b"
0k"
0l"
0u"
0v"
0!#
0"#
1&
#70000
0R"
0V"
b1110 !
b1110 -
0_"
1Q"
1"
1`"
0^
0h
0r
0|
0("
02"
0<"
0F"
0O"
0\"
0g"
0p"
0z"
0&#
1]
1b
1g
1l
1q
1v
1{
1""
1'"
1,"
11"
16"
1;"
1@"
1E"
1J"
1N"
1T"
1W"
1X"
1a"
1c"
1k"
1l"
1u"
1v"
1!#
1"#
0L"
0&
1%
#75000
0e"
1d"
0^"
0b"
0>
0M"
1B
1?
1,
0:
1^
1h
1r
1|
1("
12"
1<"
1F"
1O"
1/
1\"
1g"
1p"
1z"
1&#
0]
0b
0g
0l
0q
0v
0{
0""
0'"
0,"
01"
06"
0;"
0@"
0E"
0J"
0N"
0S"
0W"
0X"
0a"
1c"
0k"
0l"
0u"
0v"
0!#
0"#
1&
#80000
0`
0j
0t
0*"
04"
0>"
0`"
0Q"
1a
1k
1u
1+"
15"
1?"
b1111 !
b1111 -
1_"
1R"
0_
0i
0s
0|
0)"
03"
0="
0F"
0\"
0f"
0p"
0z"
0&#
0P"
1%"
1/"
19"
1[
1e
1o
1]
1b
1g
1l
1q
1v
1{
1""
1'"
1,"
11"
16"
1;"
1@"
1E"
1J"
1N"
1S"
1W"
1X"
1a"
1b"
1k"
1l"
1u"
1v"
1!#
1"#
1L"
0$"
0."
08"
0Z
0d
0n
0&
0%
b1000 $
b1000 (
b1000 #
b1000 '
#85000
0x"
0$#
0n"
1y"
1%#
1o"
0w"
0##
0m"
1r"
1|"
0d"
1h"
0*
0)
0C
1e"
0+
08
09
0A
1D
0@
0c"
0=
0K
1W
0N
1Y
0J
0L
1X
0M
1^"
1>
1V
1H
1U
1G
1T
1F
0B
0?
0,
1:
07
06
05
03
02
01
0/
1_
1\
1i
1f
1s
1p
1|
1)"
1&"
13"
10"
1="
1:"
1F"
1P"
1M"
1\"
1f"
1p"
1z"
1&#
0]
0c
0g
0m
0q
0w
0{
0""
0'"
0-"
01"
07"
0;"
0A"
0E"
0J"
0N"
0T"
0W"
0X"
0a"
1b"
0k"
1l"
0u"
1v"
0!#
1"#
1&
